orcheo_backend/__init__.py
orcheo_backend/app/__init__.py
orcheo_backend/app/_app_module.py
orcheo_backend/app/_core_exports.py
orcheo_backend/app/_router_exports.py
orcheo_backend/app/chatkit_asset_proxy.py
orcheo_backend/app/chatkit_runtime.py
orcheo_backend/app/chatkit_tokens.py
orcheo_backend/app/credential_utils.py
orcheo_backend/app/dependencies.py
orcheo_backend/app/errors.py
orcheo_backend/app/factory.py
orcheo_backend/app/history_utils.py
orcheo_backend/app/logging_config.py
orcheo_backend/app/providers.py
orcheo_backend/app/service_token_endpoints.py
orcheo_backend/app/trace_utils.py
orcheo_backend/app/workflow_execution.py
orcheo_backend/app/agentensor/checkpoint_store.py
orcheo_backend/app/authentication/__init__.py
orcheo_backend/app/authentication/authenticator.py
orcheo_backend/app/authentication/context.py
orcheo_backend/app/authentication/dependencies.py
orcheo_backend/app/authentication/errors.py
orcheo_backend/app/authentication/jwks.py
orcheo_backend/app/authentication/jwt_authenticator.py
orcheo_backend/app/authentication/jwt_helpers.py
orcheo_backend/app/authentication/policy.py
orcheo_backend/app/authentication/rate_limit.py
orcheo_backend/app/authentication/service_token_authenticator.py
orcheo_backend/app/authentication/service_tokens.py
orcheo_backend/app/authentication/settings.py
orcheo_backend/app/authentication/telemetry.py
orcheo_backend/app/authentication/utils.py
orcheo_backend/app/chatkit/__init__.py
orcheo_backend/app/chatkit/context.py
orcheo_backend/app/chatkit/in_memory_store.py
orcheo_backend/app/chatkit/message_utils.py
orcheo_backend/app/chatkit/messages.py
orcheo_backend/app/chatkit/server.py
orcheo_backend/app/chatkit/telemetry.py
orcheo_backend/app/chatkit/workflow_executor.py
orcheo_backend/app/chatkit_store_postgres/__init__.py
orcheo_backend/app/chatkit_store_postgres/attachments.py
orcheo_backend/app/chatkit_store_postgres/base.py
orcheo_backend/app/chatkit_store_postgres/items.py
orcheo_backend-0.17.2.dist-info/METADATA
orcheo_backend-0.17.2.dist-info/WHEEL
orcheo_backend-0.17.2.dist-info/entry_points.txt
orcheo_backend-0.17.2.dist-info/top_level.txt
orcheo_backend-0.17.2.dist-info/RECORD
