Metadata-Version: 2.4
Name: orcheo-backend
Version: 0.17.2
Summary: Deployment wrapper around the Orcheo FastAPI application
Requires-Python: >=3.12
Requires-Dist: fastapi>=0.104.0
Requires-Dist: uvicorn[standard]>=0.24.0
Requires-Dist: orcheo>=0.18.0
Requires-Dist: celery[redis]>=5.3.0
Requires-Dist: redis>=5.0.0
Requires-Dist: httpx>=0.25.0
Provides-Extra: dev
Requires-Dist: pytest; extra == "dev"
Requires-Dist: pytest-asyncio; extra == "dev"
Requires-Dist: pytest-cov; extra == "dev"
Requires-Dist: ruff; extra == "dev"
Requires-Dist: mypy; extra == "dev"
